codebase2prompt/__init__.py
codebase2prompt/__main__.py
codebase2prompt/cli.py
codebase2prompt/cli_commands.py
codebase2prompt/config.py
codebase2prompt/file_processor.py
codebase2prompt/formatter.py
codebase2prompt/javascript_parser.py
codebase2prompt/parser.py
codebase2prompt/scanner.py
codebase2prompt/syntax_validator.py
codebase2prompt/utils/__init__.py
codebase2prompt/utils/language_inference.py
codebase2prompt-0.1.4.dist-info/entry_points.txt
codebase2prompt-0.1.4.dist-info/LICENSE
codebase2prompt-0.1.4.dist-info/METADATA
codebase2prompt-0.1.4.dist-info/WHEEL
codebase2prompt-0.1.4.dist-info/RECORD
