Metadata-Version: 2.3
Name: codebase2prompt
Version: 0.1.4
Summary: Generate prompts from codebase structure and content
License: MIT
Keywords: llm,prompt-engineering,code-analysis,ai,developer-tools
Author: Devin Bates
Author-email: devinlbates@gmail.com
Requires-Python: >=3.8,<4.0
Classifier: Development Status :: 4 - Beta
Classifier: Intended Audience :: Developers
Classifier: License :: OSI Approved :: MIT License
Classifier: Operating System :: OS Independent
Classifier: Programming Language :: Python :: 3
Classifier: Programming Language :: Python :: 3.8
Classifier: Programming Language :: Python :: 3.9
Classifier: Programming Language :: Python :: 3.10
Classifier: Programming Language :: Python :: 3.11
Classifier: Programming Language :: Python :: 3.12
Classifier: Programming Language :: Python :: 3.13
Classifier: Topic :: Software Development :: Libraries :: Python Modules
Classifier: Topic :: Text Processing
Classifier: Topic :: Utilities
Requires-Dist: beautifulsoup4 (>=4.12.0,<5.0.0)
Requires-Dist: click (>=8.1.3,<9.0.0)
Requires-Dist: configparser (>=5.3.0,<6.0.0)
Requires-Dist: css-validator (>=0.3.0,<0.4.0)
Requires-Dist: esprima (>=4.0.1,<5.0.0)
Requires-Dist: pyperclip (>=1.8.2,<2.0.0)
Requires-Dist: pyyaml (>=6.0.1,<7.0.0)
Requires-Dist: rich (>=13.3.1,<14.0.0)
Requires-Dist: typer (>=0.9.0,<0.10.0)
Project-URL: Bug Tracker, https://github.com/epicshardz/codebase2prompt/issues
Project-URL: Documentation, https://github.com/epicshardz/codebase2prompt#readme
Project-URL: Homepage, https://github.com/epicshardz/codebase2prompt
Project-URL: Repository, https://github.com/epicshardz/codebase2prompt
